Metadata-Version: 2.1
Name: shlax
Version: 1.0.1
Summary: Beautiful Async Subprocess executor
Home-page: https://yourlabs.io/oss/shlax
Author: James Pic
Author-email: jamespic@gmail.com
License: MIT
Keywords: async subprocess
Platform: UNKNOWN
Requires-Python: >=3
Provides-Extra: test
